[
	{
		"title": "Start",
		"tags": "",
		"body": "<<move Aig StageLeft2>><<move Lee StageRight2>>\n<<outfit Lee Casual>>\n<<outfit Aig Casual>>\n<<expression Lee Neutral>>\n<<expression Aig Neutral>>\n<<name Friendship Lee>>\nHey Aigburth.\n<<name Friendship Aig>>\nSup.\n<<name Friendship Lee>>\nIt seems like you're really working hard lately. Good job.\n<<name Friendship Aig>>\nYeah! Thanks!\n<<name Friendship Lee>>\nBut just a reminder, you shouldn't be neglecting the other parts of your training. \nThe company still wants us to be well-rounded, to an extent.\n->Ugh, really?\n    <<expression Aig Angry>>\n    <<name Friendship Aig>>\n    Ugh, really?\n    <<name Friendship Lee>>\n    <<statDown Friendship Lee>>\n    <<expression Lee Angry>>\n    Yeah, really.\n->Sure thing.\n    <<name Friendship Aig>>\n    Yeah, sure thing.\n    <<name Friendship Lee>>\n    <<expression Lee Happy>>\n    <<statUp Friendship Lee>>\n    Thanks, man.\n    I know it's kind of a pain.\n    <<expression Lee Neutral>>\n<<name Friendship Lee>>\nYou know that I'm no good at promoting myself, but I still gotta try.\nSame goes for you--even if you don't think you're good at something, you should at least work on it a little.\nThey're not gonna take it easy on you just because you're the youngest, you know?\n<<name Friendship Aig>>\nYeah, yeah.",
		"position": {
			"x": 540,
			"y": 260
		},
		"colorID": 0
	}
]